{
  "predictions": [
    {
      "group": [
        10,
        10,
        10,
        10
      ],
      "score": 2.583062071904532e-06
    },
    {
      "group": [
        10,
        10,
        10,
        10
      ],
      "score": 2.583062071904532e-06
    },
    {
      "group": [
        10,
        10,
        10,
        10
      ],
      "score": 2.583062071904532e-06
    },
    {
      "group": [
        10,
        10,
        10,
        10
      ],
      "score": 2.583062071904532e-06
    },
    {
      "group": [
        10,
        10,
        10,
        10
      ],
      "score": 2.583062071904532e-06
    }
  ]
}